bits/__init__.py
bits/sftp/__init__.py
bits_sftp-1.0.1.dist-info/METADATA
bits_sftp-1.0.1.dist-info/WHEEL
bits_sftp-1.0.1.dist-info/top_level.txt
bits_sftp-1.0.1.dist-info/RECORD
