Metadata-Version: 2.1
Name: bits-sftp
Version: 1.0.1
Summary: BITS SFTP
Home-page: UNKNOWN
Author: Lukas Karlsson
Author-email: karlsson@broadinstitute.org
License: Apache Software License
Platform: UNKNOWN
Requires-Dist: paramiko
